[
  {
    "firstName": "john",
    "lastName": "paulson",
    "title": "Mr",
    "phone": "08109561020",
    "address": "No 4 yerima street Sabo Tasha",
    "country": "Nigeria",
    "email": "rexamani1221@gmail.com",
    "isChristian": "Yes",
    "intoBusiness": "Yes",
    "preferredGarment": "Kippah",
    "submittedAt": "2025-08-07T10:13:59.554Z"
  },
  {
    "firstName": "john",
    "lastName": "paulson",
    "title": "Mr",
    "phone": "08109561020",
    "address": "No 4 yerima street Sabo Tasha",
    "country": "Nigeria",
    "email": "rexamani1221@gmail.com",
    "submittedAt": "2025-08-07T14:25:34.662Z"
  },
  {
    "firstName": "john",
    "lastName": "paulson",
    "title": "Mr",
    "phone": "08109561020",
    "address": "No 4 yerima street Sabo Tasha",
    "country": "Nigeria",
    "email": "rexamani1221@gmail.com",
    "submittedAt": "2025-08-07T14:41:54.909Z"
  },
  {
    "firstName": "john",
    "lastName": "paulson",
    "title": "Mr",
    "phone": "08109561020",
    "address": "No 4 yerima street Sabo Tasha",
    "country": "Nigeria",
    "email": "rexamani1221@gmail.com",
    "submittedAt": "2025-08-08T13:34:16.458Z"
  },
  {
    "firstName": "john",
    "lastName": "paulson",
    "title": "Mr",
    "phone": "08109561020",
    "address": "No 4 yerima street Sabo Tasha",
    "country": "Nigeria",
    "email": "rexamani1221@gmail.com",
    "submittedAt": "2025-08-08T15:15:50.182Z"
  },
  {
    "firstName": "john",
    "lastName": "paulson",
    "title": "Mr",
    "phone": "08109561020",
    "address": "No 4 yerima street Sabo Tasha",
    "country": "Nigeria",
    "email": "rexamani1221@gmail.com",
    "submittedAt": "2025-08-08T21:46:08.488Z"
  },
  {
    "firstName": "samson",
    "lastName": "David",
    "title": "Mr",
    "phone": "08034630666",
    "address": "No 4 yerima street Sabo Tasha",
    "country": "Ghana",
    "email": "rexamani1211@gmail.com",
    "submittedAt": "2025-08-09T07:00:28.896Z"
  },
  {
    "firstName": "john",
    "lastName": "paulson",
    "title": "Mr",
    "phone": "08109561020",
    "address": "4 yerima street sabon tasha ",
    "country": "Nigeria",
    "email": "glitzincs@gmail.com",
    "submittedAt": "2025-08-13T09:45:44.906Z"
  },
  {
    "firstName": "john",
    "lastName": "paulson",
    "title": "Mr",
    "phone": "08109561929",
    "address": "4",
    "country": "Nigeria",
    "email": "christianjewishbelievers@gmail.com",
    "submittedAt": "2025-08-15T09:02:32.681Z"
  },
  {
    "firstName": "john",
    "lastName": "paulson",
    "title": "Mr",
    "phone": "08109561020",
    "address": "4",
    "country": "Nigeria",
    "email": "rexamani1211@gmail.com",
    "submittedAt": "2025-08-15T09:05:32.324Z"
  },
  {
    "firstName": "david",
    "lastName": "paul",
    "title": "Mr",
    "phone": "09122719293",
    "address": "4 yerima street sabon tasha ",
    "country": "Nigeria",
    "email": "glitzincs@gmail.com",
    "submittedAt": "2025-08-16T15:11:30.361Z"
  },
  {
    "firstName": "JOhn",
    "lastName": "paulson",
    "title": "Mr",
    "phone": "08109561020",
    "address": "No 4 yerima street Sabo Tasha",
    "country": "Nigeria",
    "email": "glitzincs@gmail.com",
    "submittedAt": "2025-08-25T18:09:02.113Z"
  },
  {
    "firstName": "john",
    "lastName": "paulson",
    "title": "Mr",
    "phone": "08034630666",
    "address": "No 4 yerima street Sabo Tasha",
    "country": "Nigeria",
    "email": "glitzincs@gmail.com",
    "submittedAt": "2025-08-25T18:17:31.795Z"
  },
  {
    "firstName": "John",
    "lastName": "Paulson",
    "title": "Mr",
    "phone": "08109561020",
    "address": "4",
    "country": "Nigeria",
    "email": "glitzincs@gmail.com",
    "submittedAt": "2025-08-27T14:14:23.462Z"
  },
  {
    "firstName": "john ",
    "lastName": "paulson",
    "title": "Mr",
    "phone": "08109561020",
    "address": "No 4 yerima street Sabo Tasha",
    "country": "Nigeria",
    "email": "umunnapeter3838@gmail.com",
    "submittedAt": "2025-08-27T14:44:03.219Z"
  },
  {
    "firstName": "john",
    "lastName": "paulson",
    "title": "Pastor",
    "phone": "08109561020",
    "address": "No 4 yerima street Sabo Tasha",
    "country": "Nigeria",
    "email": "rexamani1221@gmail.com",
    "submittedAt": "2025-08-27T15:01:22.037Z"
  },
  {
    "firstName": "john",
    "lastName": "paulson",
    "title": "Mr",
    "phone": "08109561020",
    "address": "No 4 yerima street Sabo Tasha",
    "country": "Nigeria",
    "email": "rexamani1221@gmail.com",
    "submittedAt": "2025-08-27T15:05:42.573Z"
  },
  {
    "firstName": "John",
    "lastName": "paulson",
    "title": "Pastor",
    "phone": "08109561929",
    "address": "No 4 yerima street Sabo Tasha",
    "country": "Nigeria",
    "email": "glitzincs@gmail.com",
    "submittedAt": "2025-08-28T17:41:48.164Z"
  },
  {
    "firstName": "John",
    "lastName": "Paulson",
    "title": "Mr",
    "phone": "08109561020",
    "address": "4 yerima street ",
    "country": "Nigeria",
    "email": "rexanabi1221@gmail.com",
    "submittedAt": "2025-09-01T10:37:38.179Z"
  },
  {
    "firstName": "John",
    "lastName": "Paulson",
    "title": "Mr",
    "phone": "08109561020",
    "address": "4 yerima street ",
    "country": "Nigeria",
    "email": "rexanabi1221@gmail.com",
    "submittedAt": "2025-09-01T10:37:47.997Z"
  }
]